pycomo/__init__.py
pycomo/pycomo_models.py
pycomo/helper/__init__.py
pycomo/helper/cli.py
pycomo/helper/logger.py
pycomo/helper/multiprocess.py
pycomo/helper/process_pool.py
pycomo/helper/utils.py
pycomo-0.2.7.dist-info/LICENSE
pycomo-0.2.7.dist-info/METADATA
pycomo-0.2.7.dist-info/WHEEL
pycomo-0.2.7.dist-info/entry_points.txt
pycomo-0.2.7.dist-info/top_level.txt
pycomo-0.2.7.dist-info/RECORD
