Metadata-Version: 2.1
Name: pycomo
Version: 0.2.7
Summary: PyCoMo is a software package for generating and analysing compartmentalized community metabolic models
Home-page: https://github.com/univieCUBE/PyCoMo
Author: Michael Predl
Author-email: Michael Predl <michael.predl@univie.ac.at>, Marianne Mießkes <marianne.miesskes@univie.ac.at>
Maintainer-email: Michael Predl <michael.predl@univie.ac.at>, Marianne Mießkes <marianne.miesskes@univie.ac.at>
License: MIT License
Project-URL: repository, https://github.com/univieCUBE/PyCoMo
Classifier: License :: OSI Approved :: MIT License
Classifier: Programming Language :: Python :: 3
Requires-Python: >=3.9
License-File: LICENSE
Requires-Dist: cobra>=0.23.0
Requires-Dist: pandas>=1.5.3
Requires-Dist: python-libsbml>=5.20.1
Requires-Dist: numpy>=1.22.4
